gnews/__init__.py
gnews/gnewsfixup.py
gnews/utils/__init__.py
gnews/utils/constants.py
gnews/utils/utils.py
gnewsfixup-0.0.5.dist-info/LICENSE.txt
gnewsfixup-0.0.5.dist-info/METADATA
gnewsfixup-0.0.5.dist-info/WHEEL
gnewsfixup-0.0.5.dist-info/top_level.txt
gnewsfixup-0.0.5.dist-info/RECORD
