Metadata-Version: 2.1
Name: gnewsfixup
Version: 0.0.5
Summary: Provide an API to search for articles on Google News and returns a usable JSON response.
Home-page: https://github.com/holygeek00/GNews/
Author: Naassh
Author-email: liuqingfeng00@gmail.com
License: UNKNOWN
Project-URL: Documentation, https://github.com/holygeek00/GNews/blob/master/README.md
Project-URL: Source, https://github.com/holygeek00/GNews/
Project-URL: Tracker, https://github.com/holygeek00/GNews/issues
Platform: UNKNOWN
Classifier: Development Status :: 5 - Production/Stable
Classifier: Intended Audience :: Developers
Classifier: Programming Language :: Python :: 3
Classifier: Programming Language :: Python :: 3.8
Classifier: Programming Language :: Python :: 3.9
Classifier: Programming Language :: Python :: 3.10
Classifier: Programming Language :: Python :: 3.11
Classifier: License :: OSI Approved :: MIT License
Classifier: Operating System :: OS Independent
License-File: LICENSE.txt
Requires-Dist: feedparser (~=6.0.2)
Requires-Dist: beautifulsoup4 (<5,>=4.9.3)
Requires-Dist: dnspython
Requires-Dist: requests
